README.rst
setup.py
time_uuid/__init__.py
time_uuid.egg-info/PKG-INFO
time_uuid.egg-info/SOURCES.txt
time_uuid.egg-info/dependency_links.txt
time_uuid.egg-info/top_level.txt